<?xml version="1.0" encoding="UTF-8"?>
<persistence version="2.1" xmlns="http://xmlns.jcp.org/xml/ns/persistence" xmlns:xsi="http://www.w3.org/2001/XMLSchema-instance" xsi:schemaLocation="http://xmlns.jcp.org/xml/ns/persistence http://xmlns.jcp.org/xml/ns/persistence/persistence_2_1.xsd">
	<persistence-unit name="api" transaction-type="RESOURCE_LOCAL">
	 <provider>org.eclipse.persistence.jpa.PersistenceProvider</provider>
	 <class>medicamp.model.Activiteit</class>
	 <class>medicamp.model.Dieet</class>
	 <class>medicamp.model.Groep</class>
	 <class>medicamp.model.Kind</class>
	 <class>medicamp.model.Medicatie</class>
	 <class>medicamp.model.Tak</class>
	 <class>medicamp.model.Tijdstip</class>
	 <class>medicamp.model.User</class>
	 <class>medicamp.model.Voogd</class>
	 <class>medicamp.model.Ziekte</class>
  <exclude-unlisted-classes>false</exclude-unlisted-classes>
	
	<properties>
      <property name="javax.persistence.jdbc.url" value="jdbc:mysql://35.195.195.51:3306/medicamp_test"/>
      <property name="javax.persistence.jdbc.user" value="root"/>
      <property name="javax.persistence.jdbc.driver" value="com.mysql.jdbc.Driver"/>
      <property name="javax.persistence.jdbc.password" value="ApSO1718m"/>
<!--       <property name="javax.persistence.schema-generation.database.action" value="create"/> -->
    </properties>
	</persistence-unit>
</persistence>
